cloudml/__init__.py
cloudml/adrn_dataloader.py
cloudml/adrn_dataset.py
cloudml/adrn_parser.py
cloudml/dataset_srv_stub.py
cloudml/item_handler.py
cloudml/settings.py
cloudml/test_code.py
cloudml/thetis_dataset.py
cloudml_pytorch_assistant-0.0.1a1.dist-info/DESCRIPTION.rst
cloudml_pytorch_assistant-0.0.1a1.dist-info/METADATA
cloudml_pytorch_assistant-0.0.1a1.dist-info/RECORD
cloudml_pytorch_assistant-0.0.1a1.dist-info/WHEEL
cloudml_pytorch_assistant-0.0.1a1.dist-info/metadata.json
cloudml_pytorch_assistant-0.0.1a1.dist-info/top_level.txt
